tag_factory_cli/__init__.py
tag_factory_cli/cli.py
tag_factory_cli/datasets.py
tag_factory_cli/hashtags.py
tag_factory_cli/tags.py
tag_factory_cli/workspaces.py
tag_factory_cli/utils/__init__.py
tag_factory_cli/utils/api.py
tag_factory_cli/utils/config.py
tag_factory-0.1.1.dist-info/METADATA
tag_factory-0.1.1.dist-info/WHEEL
tag_factory-0.1.1.dist-info/entry_points.txt
tag_factory-0.1.1.dist-info/top_level.txt
tag_factory-0.1.1.dist-info/RECORD
