Metadata-Version: 2.4
Name: tag-factory
Version: 0.1.1
Summary: CLI tool for Tag Factory
Author: Tag Factory Team
License: MIT
Project-URL: Homepage, https://github.com/tag-factory/tag-factory
Project-URL: Bug Tracker, https://github.com/tag-factory/tag-factory/issues
Classifier: Programming Language :: Python :: 3
Classifier: Programming Language :: Python :: 3.8
Classifier: Programming Language :: Python :: 3.9
Classifier: Programming Language :: Python :: 3.10
Classifier: License :: OSI Approved :: MIT License
Classifier: Operating System :: OS Independent
Requires-Python: >=3.8
Requires-Dist: click
Requires-Dist: requests
Requires-Dist: pydantic
Requires-Dist: tqdm
